tabarena/__init__.py
tabarena-0.0.0.dist-info/METADATA
tabarena-0.0.0.dist-info/WHEEL
tabarena-0.0.0.dist-info/top_level.txt
tabarena-0.0.0.dist-info/RECORD
