Metadata-Version: 2.4
Name: tabarena
Version: 0.0.0
Summary: Coming soon
Author-email: TabArena Team <contact@tabarena.ai>
